triton.pyi
triton.cpython-310-darwin.so
triton_library.dylibs/libc++abi.1.0.dylib
triton_library.dylibs/libbitwuzlabv.dylib
triton_library.dylibs/libRemarks.dylib
triton_library.dylibs/libc++.1.0.dylib
triton_library.dylibs/libbitwuzla.0.dylib
triton_library.dylibs/libbitwuzlals.dylib
triton_library.dylibs/libbitwuzlabb.dylib
triton_library.dylibs/libLTO.dylib
triton_library.dylibs/libgmp.10.dylib
triton_library-1.0.0rc4.dist-info/RECORD
triton_library-1.0.0rc4.dist-info/WHEEL
triton_library-1.0.0rc4.dist-info/top_level.txt
triton_library-1.0.0rc4.dist-info/LICENSE.txt
triton_library-1.0.0rc4.dist-info/METADATA
