Metadata-Version: 2.1
Name: triton-library
Version: 1.0.0rc4
Summary: Triton is a dynamic binary analysis library
Author: The Triton's community
Author-email: tritonlibrary@gmail.com
License: Apache License Version 2.0
Project-URL: Homepage, https://triton-library.github.io/
Project-URL: Source, https://github.com/jonathansalwan/Triton
Classifier: Programming Language :: C++
Classifier: Programming Language :: Python :: 3
Classifier: Topic :: Security
Classifier: Topic :: Software Development :: Libraries
Requires-Python: >=3.6
License-File: LICENSE.txt
